odoo/addons/agreement_serviceprofile/README.rst
odoo/addons/agreement_serviceprofile/__init__.py
odoo/addons/agreement_serviceprofile/__manifest__.py
odoo/addons/agreement_serviceprofile/data/serviceprofile_stage.xml
odoo/addons/agreement_serviceprofile/i18n/agreement_serviceprofile.pot
odoo/addons/agreement_serviceprofile/i18n/de.po
odoo/addons/agreement_serviceprofile/i18n/en_US.po
odoo/addons/agreement_serviceprofile/i18n/es.po
odoo/addons/agreement_serviceprofile/i18n/fr.po
odoo/addons/agreement_serviceprofile/i18n/pt.po
odoo/addons/agreement_serviceprofile/i18n/pt_BR.po
odoo/addons/agreement_serviceprofile/i18n/zh_CN.po
odoo/addons/agreement_serviceprofile/models/__init__.py
odoo/addons/agreement_serviceprofile/models/agreement.py
odoo/addons/agreement_serviceprofile/models/agreement_serviceprofile.py
odoo/addons/agreement_serviceprofile/models/agreement_stage.py
odoo/addons/agreement_serviceprofile/models/product.py
odoo/addons/agreement_serviceprofile/readme/CONTRIBUTORS.rst
odoo/addons/agreement_serviceprofile/readme/DESCRIPTION.rst
odoo/addons/agreement_serviceprofile/security/ir.model.access.csv
odoo/addons/agreement_serviceprofile/static/description/icon.png
odoo/addons/agreement_serviceprofile/static/description/index.html
odoo/addons/agreement_serviceprofile/views/agreement.xml
odoo/addons/agreement_serviceprofile/views/agreement_serviceprofile.xml
odoo/addons/agreement_serviceprofile/views/product.xml
odoo12_addon_agreement_serviceprofile-12.0.1.2.1.dist-info/METADATA
odoo12_addon_agreement_serviceprofile-12.0.1.2.1.dist-info/WHEEL
odoo12_addon_agreement_serviceprofile-12.0.1.2.1.dist-info/top_level.txt
odoo12_addon_agreement_serviceprofile-12.0.1.2.1.dist-info/RECORD
